{
    "display": {
        "icon": {
            "item": "minecraft:warped_fungus_on_a_stick",
            "nbt": "{CustomModelData:982023}"
        },
        "title": "Void Weaponry",
        "description": {
            "translate": "Create a Void Razor",
            "color": "gray"
        },
        "frame": "task",
        "show_toast": true,
        "announce_to_chat": true,
        "hidden": false
    },
    "parent": "gen:story/weapons/shaded_dagger",
    "criteria": {
        "weapon": {
            "trigger": "minecraft:inventory_changed",
            "conditions": {
                "items": [
                    {
                        "items": [
                            "minecraft:warped_fungus_on_a_stick"
                        ],
                        "nbt": "{gen:{name:\"void_razor\"}}"
                    }
                ]
            }
        }
    }
}
