{
    "display": {
        "icon": {
            "item": "minecraft:diamond_boots",
            "nbt": "{Trim:{material:\"emerald\", pattern:\"minecraft:silence\"}}"
        },
        "title": "I would walk 500 Miles",
        "description": {
            "translate": "Create Terra-Treader Boots",
            "color": "gray"
        },
        "frame": "task",
        "show_toast": true,
        "announce_to_chat": true,
        "hidden": false
    },
    "parent": "gen:story/speed_boots/cloud_treader",
    "criteria": {
        "boots": {
            "trigger": "minecraft:inventory_changed",
            "conditions": {
                "items": [
                    {
                        "items": [
                            "minecraft:diamond_boots"
                        ],
                        "nbt": "{gen:{name:\"terratreader_boots\"}}"
                    }
                ]
            }
        }
    }
}
